slashcmdreg/__init__.py
slashcmdreg/command.py
slashcmdreg/exceptions.py
slashcmdreg/registry.py
slashcmdreg/utils.py
slashcmdreg-4.3.1.dist-info/METADATA
slashcmdreg-4.3.1.dist-info/WHEEL
slashcmdreg-4.3.1.dist-info/top_level.txt
slashcmdreg-4.3.1.dist-info/RECORD
