Metadata-Version: 2.4
Name: slashcmdreg
Version: 4.3.1
Summary: Modular slash command registry for Discord bots written in Python
Author: TrianglumDev
License: MIT
Requires-Python: >=3.8
Requires-Dist: discord.py
